rowantree/content/service/__init__.py
rowantree/content/service/server.py
rowantree/content/service/common/__init__.py
rowantree/content/service/common/abstract/__init__.py
rowantree/content/service/common/abstract/abstract_loremaster.py
rowantree/content/service/common/abstract/abstract_personality.py
rowantree/content/service/common/world/__init__.py
rowantree/content/service/common/world/events.json
rowantree/content/service/common/world/personality.py
rowantree/content/service/common/world/storyteller.py
rowantree/content/service/utils/__init__.py
rowantree/content/service/utils/log.py
rowantree.content.service-0.20.0.dist-info/LICENSE
rowantree.content.service-0.20.0.dist-info/METADATA
rowantree.content.service-0.20.0.dist-info/WHEEL
rowantree.content.service-0.20.0.dist-info/top_level.txt
rowantree.content.service-0.20.0.dist-info/RECORD
