Metadata-Version: 2.1
Name: rowantree.content.service
Version: 0.20.0
Summary: The Rowan Tree Content Service
Author: Joshua C. Burt
Author-email: joshburt@shapeandshare.com
License: MIT
Requires-Python: >=3.9
License-File: LICENSE
Requires-Dist: pydantic (~=1.10)
Requires-Dist: python-jose (~=3.3)
Requires-Dist: rowantree.contracts (~=0.16)
Requires-Dist: rowantree.common.sdk (~=0.4)
Requires-Dist: rowantree.auth.sdk (~=0.20)
Requires-Dist: rowantree.game.service.sdk (~=0.27)
